README.txt
setup.cfg
setup.py
jbcnfw.egg-info/PKG-INFO
jbcnfw.egg-info/SOURCES.txt
jbcnfw.egg-info/dependency_links.txt
jbcnfw.egg-info/not-zip-safe
jbcnfw.egg-info/requires.txt
jbcnfw.egg-info/top_level.txt
resource/__init__.py
resource/app.py