Metadata-Version: 1.0
Name: jbcnfw
Version: 0.1
Summary: Resource traversal app
Home-page: UNKNOWN
Author: Neal Williams
Author-email: nealfwilliams@gmail.com
License: UNKNOWN
Platform: UNKNOWN
